{
  "metadata": {
    "generated_at": "2025-08-26T12:20:51.707845",
    "generator": "Interactive Internet Plan Advisor Data Fetcher",
    "version": "1.0",
    "count": 87
  },
  "data": [
    {
      "name": "10MATES",
      "website": "https://10mates.com.au/",
      "logo_url": null,
      "active": true,
      "support_email": "support@10MATES.com.au",
      "support_phone": "1300 030 692",
      "id": 1,
      "created_at": "2025-06-20T02:46:43Z",
      "network_details": []
    },
    {
      "name": "2IT TECHNOLOGY",
      "website": "https://www.2ittech.com.au/",
      "logo_url": null,
      "active": true,
      "support_email": null,
      "support_phone": "07 4911 4161",
      "id": 3,
      "created_at": "2025-06-20T02:46:43Z",
      "network_details": []
    },
    {
      "name": "8NETWORKS",
      "website": "https://8networks.com.au/",
      "logo_url": null,
      "active": true,
      "support_email": "info@8networks.com.au",
      "support_phone": "1800 921 212",
      "id": 156,
      "created_at": "2025-07-18T10:43:05Z",
      "network_details": []
    },
    {
      "name": "ACE INTERNET",
      "website": "https://ace.com.au/",
      "logo_url": null,
      "active": true,
      "support_email": "info@ace.com.au",
      "support_phone": "1300 360 979",
      "id": 5,
      "created_at": "2025-06-20T02:46:43Z",
      "network_details": []
    },
    {
      "name": "ACTIV8ME",
      "website": "https://www.activ8me.net.au/",
      "logo_url": null,
      "active": true,
      "support_email": "",
      "support_phone": "13 22 88",
      "id": 6,
      "created_at": "2025-06-20T02:46:43Z",
      "network_details": []
    },
    {
      "name": "ADVANTAGE COMMUNICATION & DATA",
      "website": "https://www.advantagecom.com.au/",
      "logo_url": null,
      "active": true,
      "support_email": "servicedesk@advantagecom.com.au",
      "support_phone": "1300 264 860",
      "id": 9,
      "created_at": "2025-06-20T02:46:43Z",
      "network_details": []
    },
    {
      "name": "AGL TELECOMMUNICATIONS",
      "website": "https://www.agl.com.au/",
      "logo_url": null,
      "active": true,
      "support_email": "",
      "support_phone": "131 245",
      "id": 10,
      "created_at": "2025-06-20T02:46:43Z",
      "network_details": []
    },
    {
      "name": "ANT",
      "website": "http://www.ant.com.au/",
      "logo_url": null,
      "active": true,
      "support_email": "",
      "support_phone": "1300 268 266",
      "id": 14,
      "created_at": "2025-06-20T02:46:43Z",
      "network_details": []
    },
    {
      "name": "AQUA MOBILE",
      "website": "https://www.aquamobile.net.au/",
      "logo_url": null,
      "active": true,
      "support_email": "support@aquamobile.net.au",
      "support_phone": "1300 097 819",
      "id": 15,
      "created_at": "2025-06-20T02:46:43Z",
      "network_details": []
    },
    {
      "name": "AUS INTERNET",
      "website": "https://ausinternet.com.au/",
      "logo_url": null,
      "active": true,
      "support_email": "support@ausinternet.com.au",
      "support_phone": "07 4222-1111 ",
      "id": 18,
      "created_at": "2025-06-20T02:46:43Z",
      "network_details": []
    },
    {
      "name": "AUSSIE BROADBAND",
      "website": "https://www.aussiebroadband.com.au/",
      "logo_url": null,
      "active": true,
      "support_email": "",
      "support_phone": "1300 880 905",
      "id": 20,
      "created_at": "2025-06-20T02:46:43Z",
      "network_details": []
    },
    {
      "name": "BELONG",
      "website": "https://www.belong.com.au/",
      "logo_url": null,
      "active": true,
      "support_email": "",
      "support_phone": "1300 235 664",
      "id": 27,
      "created_at": "2025-06-20T02:46:43Z",
      "network_details": []
    },
    {
      "name": "BUDDY TELCO",
      "website": "https://Buddytelco.com.au",
      "logo_url": null,
      "active": true,
      "support_email": "Unknown",
      "support_phone": "",
      "id": 32,
      "created_at": "2025-06-20T02:46:43Z",
      "network_details": []
    },
    {
      "name": "CARBON COMMS",
      "website": "https://carboncomms.com.au/",
      "logo_url": null,
      "active": true,
      "support_email": "hello@carboncomms.com.au",
      "support_phone": "1800 10 10 50",
      "id": 37,
      "created_at": "2025-06-20T02:46:43Z",
      "network_details": []
    },
    {
      "name": "CLICK ACCESS",
      "website": "https://www.clickaccess.com.au/",
      "logo_url": null,
      "active": true,
      "support_email": "info@clickaccess.com.au",
      "support_phone": "07 5315 5440",
      "id": 41,
      "created_at": "2025-06-20T02:46:43Z",
      "network_details": []
    },
    {
      "name": "CMOBILE",
      "website": "https://www.cmobile.com.au/",
      "logo_url": null,
      "active": true,
      "support_email": "support@cmobile.com.au",
      "support_phone": "1300 545 000",
      "id": 42,
      "created_at": "2025-06-20T02:46:43Z",
      "network_details": []
    },
    {
      "name": "CONNECTED AUSTRALIA",
      "website": "https://www.connectedoz.com.au/",
      "logo_url": null,
      "active": true,
      "support_email": "support@connectedoz.com.au",
      "support_phone": "1300 859 778",
      "id": 43,
      "created_at": "2025-06-20T02:46:43Z",
      "network_details": []
    },
    {
      "name": "DODO",
      "website": "https://www.dodo.com/",
      "logo_url": null,
      "active": true,
      "support_email": "",
      "support_phone": "13 36 36",
      "id": 48,
      "created_at": "2025-06-20T02:46:43Z",
      "network_details": []
    },
    {
      "name": "EHW TECHNOLOGY",
      "website": "https://www.ehw.net.au/",
      "logo_url": null,
      "active": true,
      "support_email": "sales@ehwtech.net.au",
      "support_phone": "(07) 4944 0111",
      "id": 51,
      "created_at": "2025-06-20T02:46:43Z",
      "network_details": []
    },
    {
      "name": "ELEVATE",
      "website": "https://www.elevateinternet.com.au/",
      "logo_url": null,
      "active": true,
      "support_email": "support@elevateinternet.com.au",
      "support_phone": "1300 191 845",
      "id": 157,
      "created_at": "2025-07-18T10:55:41Z",
      "network_details": []
    },
    {
      "name": "ESCAPENET",
      "website": "https://www.esc.net.au/",
      "logo_url": null,
      "active": true,
      "support_email": "support@team.esc.net.au",
      "support_phone": "1300 135 235",
      "id": 52,
      "created_at": "2025-06-20T02:46:43Z",
      "network_details": []
    },
    {
      "name": "EXETEL",
      "website": "http://www.exetel.com.au/",
      "logo_url": null,
      "active": true,
      "support_email": null,
      "support_phone": null,
      "id": 53,
      "created_at": "2025-06-20T02:46:43Z",
      "network_details": []
    },
    {
      "name": "FANTEL",
      "website": "http://fantel.com.au/",
      "logo_url": null,
      "active": true,
      "support_email": "support@fantel.com.au",
      "support_phone": "+61 2 8332 3030",
      "id": 55,
      "created_at": "2025-06-20T02:46:43Z",
      "network_details": []
    },
    {
      "name": "FLIP",
      "website": "https://www.flipconnect.com.au",
      "logo_url": null,
      "active": true,
      "support_email": "",
      "support_phone": "1300 354 788",
      "id": 57,
      "created_at": "2025-06-20T02:46:43Z",
      "network_details": []
    },
    {
      "name": "FRANKSTON INTERNET",
      "website": "http://franktel.com.au/",
      "logo_url": null,
      "active": true,
      "support_email": "",
      "support_phone": "03 9039 5550",
      "id": 59,
      "created_at": "2025-06-20T02:46:43Z",
      "network_details": []
    },
    {
      "name": "FUTURE BROADBAND",
      "website": "https://futurebroadband.com.au/",
      "logo_url": null,
      "active": true,
      "support_email": "",
      "support_phone": "08 6117 0600",
      "id": 60,
      "created_at": "2025-06-20T02:46:43Z",
      "network_details": []
    },
    {
      "name": "GOINTERNET",
      "website": "http://www.gointernet.net.au/",
      "logo_url": null,
      "active": true,
      "support_email": "support@gointernet.net.au",
      "support_phone": "1300 467 283",
      "id": 64,
      "created_at": "2025-06-20T02:46:43Z",
      "network_details": []
    },
    {
      "name": "GOODTEL",
      "website": "https://www.goodtel.com.au/",
      "logo_url": null,
      "active": true,
      "support_email": "",
      "support_phone": "1800 114 663",
      "id": 65,
      "created_at": "2025-06-20T02:46:43Z",
      "network_details": []
    },
    {
      "name": "HARBOUR ISP",
      "website": "https://harbourisp.com.au",
      "logo_url": null,
      "active": true,
      "support_email": "support@harbourisp.com.au",
      "support_phone": "1300 579 403",
      "id": 67,
      "created_at": "2025-06-20T02:46:43Z",
      "network_details": []
    },
    {
      "name": "IIG",
      "website": "https://www.iig.com.au/",
      "logo_url": null,
      "active": true,
      "support_email": "",
      "support_phone": "1300 552 795",
      "id": 71,
      "created_at": "2025-06-20T02:46:43Z",
      "network_details": []
    },
    {
      "name": "IINET",
      "website": "https://www.iinet.net.au/",
      "logo_url": null,
      "active": true,
      "support_email": null,
      "support_phone": null,
      "id": 72,
      "created_at": "2025-06-20T02:46:43Z",
      "network_details": []
    },
    {
      "name": "I.NET.AU",
      "website": "http://www.i.net.au/",
      "logo_url": null,
      "active": true,
      "support_email": null,
      "support_phone": null,
      "id": 69,
      "created_at": "2025-06-20T02:46:43Z",
      "network_details": []
    },
    {
      "name": "INFINET BROADBAND",
      "website": "https://www.infinetbroadband.com.au/",
      "logo_url": null,
      "active": true,
      "support_email": "sales@infinetbroadband.com.au",
      "support_phone": "1300 101 414",
      "id": 73,
      "created_at": "2025-06-20T02:46:43Z",
      "network_details": []
    },
    {
      "name": "INSPIRED BROADBAND",
      "website": "http://www.inspiredbroadband.com.au/",
      "logo_url": null,
      "active": true,
      "support_email": null,
      "support_phone": null,
      "id": 74,
      "created_at": "2025-06-20T02:46:43Z",
      "network_details": []
    },
    {
      "name": "IPRIMUS - 1300 FIBRE 1",
      "website": "https://www.iprimus.com.au/",
      "logo_url": null,
      "active": true,
      "support_email": null,
      "support_phone": null,
      "id": 77,
      "created_at": "2025-06-20T02:46:43Z",
      "network_details": []
    },
    {
      "name": "IT'S FUBAR",
      "website": "https://www.itsfubar.com.au/",
      "logo_url": null,
      "active": true,
      "support_email": "support@itsfubar.com.au",
      "support_phone": "(03) 5292 3655",
      "id": 154,
      "created_at": "2025-07-05T09:27:24Z",
      "network_details": []
    },
    {
      "name": "KINETIX",
      "website": "http://kinetix.net.au",
      "logo_url": null,
      "active": true,
      "support_email": null,
      "support_phone": null,
      "id": 81,
      "created_at": "2025-06-20T02:46:43Z",
      "network_details": []
    },
    {
      "name": "KLOUDPHONE",
      "website": "https://kloudphone.com.au/",
      "logo_url": null,
      "active": true,
      "support_email": "sales@kloudphone.com.au",
      "support_phone": "1300 525 563",
      "id": 82,
      "created_at": "2025-06-20T02:46:43Z",
      "network_details": []
    },
    {
      "name": "KOGAN",
      "website": "https://www.koganinternet.com.au/",
      "logo_url": null,
      "active": true,
      "support_email": null,
      "support_phone": null,
      "id": 83,
      "created_at": "2025-06-20T02:46:43Z",
      "network_details": []
    },
    {
      "name": "LAUNTEL",
      "website": "https://launtel.net.au/",
      "logo_url": null,
      "active": true,
      "support_email": null,
      "support_phone": null,
      "id": 84,
      "created_at": "2025-06-20T02:46:43Z",
      "network_details": []
    },
    {
      "name": "LEAPTEL",
      "website": "https://leaptel.com.au/",
      "logo_url": null,
      "active": true,
      "support_email": null,
      "support_phone": null,
      "id": 85,
      "created_at": "2025-06-20T02:46:43Z",
      "network_details": []
    },
    {
      "name": "LIGHTNING IP",
      "website": "https://www.lightningip.com.au/",
      "logo_url": null,
      "active": true,
      "support_email": null,
      "support_phone": null,
      "id": 86,
      "created_at": "2025-06-20T02:46:43Z",
      "network_details": []
    },
    {
      "name": "LIZZY INTERNET",
      "website": "https://www.lizzy.com.au/",
      "logo_url": null,
      "active": true,
      "support_email": null,
      "support_phone": null,
      "id": 88,
      "created_at": "2025-06-20T02:46:43Z",
      "network_details": []
    },
    {
      "name": "MAD OVER TECH",
      "website": "https://madovertech.com.au/",
      "logo_url": null,
      "active": true,
      "support_email": null,
      "support_phone": null,
      "id": 89,
      "created_at": "2025-06-20T02:46:43Z",
      "network_details": []
    },
    {
      "name": "MATE",
      "website": "https://www.letsbemates.com.au",
      "logo_url": null,
      "active": true,
      "support_email": null,
      "support_phone": null,
      "id": 90,
      "created_at": "2025-06-20T02:46:43Z",
      "network_details": []
    },
    {
      "name": "MATILDA",
      "website": "https://www.matilda.net.au/",
      "logo_url": null,
      "active": true,
      "support_email": null,
      "support_phone": null,
      "id": 91,
      "created_at": "2025-06-20T02:46:43Z",
      "network_details": []
    },
    {
      "name": "MAXO TELECOMMUNICATIONS",
      "website": "https://www.maxo.com.au/",
      "logo_url": null,
      "active": true,
      "support_email": "",
      "support_phone": "1800 12 12 10",
      "id": 158,
      "created_at": "2025-07-18T11:02:28Z",
      "network_details": []
    },
    {
      "name": "MOOSE MOBILE",
      "website": "https://moosemobile.com.au/",
      "logo_url": null,
      "active": true,
      "support_email": "admin@moosemobile.com.au",
      "support_phone": "1300 566 673",
      "id": 96,
      "created_at": "2025-06-20T02:46:43Z",
      "network_details": []
    },
    {
      "name": "MORE",
      "website": "https://www.more.com.au",
      "logo_url": null,
      "active": true,
      "support_email": null,
      "support_phone": null,
      "id": 97,
      "created_at": "2025-06-20T02:46:43Z",
      "network_details": []
    },
    {
      "name": "MPHONE",
      "website": "https://mphone.com.au/",
      "logo_url": null,
      "active": true,
      "support_email": null,
      "support_phone": null,
      "id": 168,
      "created_at": "2025-06-20T02:46:43Z",
      "network_details": []
    },
    {
      "name": "MYOWN TEL",
      "website": "https://www.myowntel.net.au/",
      "logo_url": null,
      "active": true,
      "support_email": null,
      "support_phone": null,
      "id": 101,
      "created_at": "2025-06-20T02:46:43Z",
      "network_details": []
    },
    {
      "name": "NATAN",
      "website": "https://natan.com.au/",
      "logo_url": null,
      "active": true,
      "support_email": null,
      "support_phone": null,
      "id": 167,
      "created_at": "2025-06-20T02:46:43Z",
      "network_details": []
    },
    {
      "name": "NEPTUNE",
      "website": "https://www.neptune.net.au/",
      "logo_url": null,
      "active": true,
      "support_email": "support@neptune.net.au",
      "support_phone": "",
      "id": 153,
      "created_at": "2025-06-23T03:37:08Z",
      "network_details": []
    },
    {
      "name": "NEW SPROUT",
      "website": "https://www.newsprout.com.au/",
      "logo_url": null,
      "active": true,
      "support_email": null,
      "support_phone": null,
      "id": 103,
      "created_at": "2025-06-20T02:46:43Z",
      "network_details": []
    },
    {
      "name": "OCCOM",
      "website": "http://occom.com.au/",
      "logo_url": null,
      "active": true,
      "support_email": "support@occom.com.au",
      "support_phone": "1300 299 999",
      "id": 108,
      "created_at": "2025-06-20T02:46:43Z",
      "network_details": []
    },
    {
      "name": "OPTUS",
      "website": "https://www.optus.com.au/",
      "logo_url": null,
      "active": true,
      "support_email": null,
      "support_phone": null,
      "id": 110,
      "created_at": "2025-06-20T02:46:43Z",
      "network_details": []
    },
    {
      "name": "ORIGIN BROADBAND",
      "website": "https://www.originenergy.com.au/",
      "logo_url": null,
      "active": true,
      "support_email": null,
      "support_phone": null,
      "id": 111,
      "created_at": "2025-06-20T02:46:43Z",
      "network_details": []
    },
    {
      "name": "OZOT",
      "website": "https://ozot.com.au/",
      "logo_url": null,
      "active": true,
      "support_email": "support@ozot.com.au",
      "support_phone": "",
      "id": 159,
      "created_at": "2025-07-18T11:06:31Z",
      "network_details": []
    },
    {
      "name": "PEAR",
      "website": "https://peartelco.com.au/",
      "logo_url": null,
      "active": true,
      "support_email": "hello@peartelco.com.au",
      "support_phone": "1300 007 327",
      "id": 112,
      "created_at": "2025-06-20T02:46:43Z",
      "network_details": []
    },
    {
      "name": "PENTANET",
      "website": "https://pentanet.com.au/",
      "logo_url": null,
      "active": true,
      "support_email": null,
      "support_phone": null,
      "id": 113,
      "created_at": "2025-06-20T02:46:43Z",
      "network_details": []
    },
    {
      "name": "QUOKKA NET",
      "website": "https://quokkanet.au/",
      "logo_url": null,
      "active": true,
      "support_email": "qwerty@quokkanet.au",
      "support_phone": "1800 663 977",
      "id": 166,
      "created_at": "2025-06-20T02:46:43Z",
      "network_details": []
    },
    {
      "name": "QURED",
      "website": "http://www.qured.com.au/",
      "logo_url": null,
      "active": true,
      "support_email": "support@qured.com.au",
      "support_phone": "1300841127",
      "id": 117,
      "created_at": "2025-06-20T02:46:43Z",
      "network_details": []
    },
    {
      "name": "REAL WORLD TECHNOLOGY SOLUTIONS",
      "website": "https://rwts.com.au/",
      "logo_url": null,
      "active": true,
      "support_email": "",
      "support_phone": "1300 798 718",
      "id": 118,
      "created_at": "2025-06-20T02:46:43Z",
      "network_details": []
    },
    {
      "name": "SKYMESH",
      "website": "https://www.skymesh.net.au/",
      "logo_url": null,
      "active": true,
      "support_email": "",
      "support_phone": "1300 759 637",
      "id": 120,
      "created_at": "2025-06-20T02:46:43Z",
      "network_details": []
    },
    {
      "name": "SOLITARY TECHNOLOGY",
      "website": "https://solitarytech.com.au/",
      "logo_url": null,
      "active": true,
      "support_email": "hello@solitarytech.com.au",
      "support_phone": "1300 914 278",
      "id": 160,
      "created_at": "2025-07-18T11:38:14Z",
      "network_details": []
    },
    {
      "name": "SOUTHERN PHONE",
      "website": "https://www.southernphone.com.au/",
      "logo_url": null,
      "active": true,
      "support_email": "",
      "support_phone": "13 14 64",
      "id": 121,
      "created_at": "2025-06-20T02:46:43Z",
      "network_details": []
    },
    {
      "name": "SPINTEL",
      "website": "https://www.spintel.net.au/",
      "logo_url": null,
      "active": true,
      "support_email": "",
      "support_phone": "13 22 10",
      "id": 122,
      "created_at": "2025-06-20T02:46:43Z",
      "network_details": [
        {
          "provider_id": 122,
          "connection_method": "DHCP",
          "vlan_required": true,
          "vlan_id": 0,
          "ipv6_supported": true,
          "default_ipv4_type": "CGNAT",
          "static_ip_cost": 0.0,
          "policy_notes": "string",
          "id": 1,
          "created_at": "2025-08-15T12:56:43.730016Z",
          "updated_at": "2025-08-15T12:56:43.730016Z"
        }
      ]
    },
    {
      "name": "STEELE TECHNOLOGY",
      "website": "https://www.stech.com.au/",
      "logo_url": null,
      "active": true,
      "support_email": null,
      "support_phone": null,
      "id": 124,
      "created_at": "2025-06-20T02:46:43Z",
      "network_details": []
    },
    {
      "name": "SUMO",
      "website": "https://www.sumo.com.au/",
      "logo_url": null,
      "active": true,
      "support_email": "",
      "support_phone": "03 9102 8400 ",
      "id": 125,
      "created_at": "2025-06-20T02:46:43Z",
      "network_details": []
    },
    {
      "name": "SUPERLOOP",
      "website": "https://superloop.com/",
      "logo_url": null,
      "active": true,
      "support_email": "",
      "support_phone": "1800 57 87 37",
      "id": 126,
      "created_at": "2025-06-20T02:46:43Z",
      "network_details": []
    },
    {
      "name": "SWOOP",
      "website": "https://swoop.com.au/",
      "logo_url": null,
      "active": true,
      "support_email": "support@swoop.com.au",
      "support_phone": "1300 66 55 75",
      "id": 128,
      "created_at": "2025-06-20T02:46:43Z",
      "network_details": []
    },
    {
      "name": "TANGERINE TELECOM",
      "website": "https://www.tangerine.com.au/",
      "logo_url": null,
      "active": true,
      "support_email": "",
      "support_phone": "1800 211 112",
      "id": 130,
      "created_at": "2025-06-20T02:46:43Z",
      "network_details": []
    },
    {
      "name": "TASMANET",
      "website": "https://www.tasmanet.com.au/",
      "logo_url": null,
      "active": true,
      "support_email": "sales@tasmanet.com.au",
      "support_phone": "1300 792 711",
      "id": 131,
      "created_at": "2025-06-20T02:46:43Z",
      "network_details": []
    },
    {
      "name": "TELSIM",
      "website": "https://www.telsim.com.au/",
      "logo_url": null,
      "active": true,
      "support_email": "",
      "support_phone": "1300 835 746",
      "id": 155,
      "created_at": "2025-07-18T10:36:52Z",
      "network_details": []
    },
    {
      "name": "TELSTRA",
      "website": "https://www.telstra.com.au/",
      "logo_url": null,
      "active": true,
      "support_email": null,
      "support_phone": null,
      "id": 133,
      "created_at": "2025-06-20T02:46:43Z",
      "network_details": []
    },
    {
      "name": "THE GEORGE BAINI GROUP",
      "website": "https://www.gb.com.au/",
      "logo_url": null,
      "active": true,
      "support_email": null,
      "support_phone": null,
      "id": 134,
      "created_at": "2025-06-20T02:46:43Z",
      "network_details": []
    },
    {
      "name": "THE INTERNET PROVIDER",
      "website": "http://theinternetprovider.com.au/",
      "logo_url": null,
      "active": true,
      "support_email": null,
      "support_phone": null,
      "id": 135,
      "created_at": "2025-06-20T02:46:43Z",
      "network_details": []
    },
    {
      "name": "TPG",
      "website": "https://www.tpg.com.au/",
      "logo_url": null,
      "active": true,
      "support_email": null,
      "support_phone": null,
      "id": 138,
      "created_at": "2025-06-20T02:46:43Z",
      "network_details": []
    },
    {
      "name": "UPLINK ME",
      "website": "https://uplinkme.com.au/",
      "logo_url": null,
      "active": true,
      "support_email": "",
      "support_phone": "1300 510 610",
      "id": 163,
      "created_at": "2025-06-20T02:46:43Z",
      "network_details": []
    },
    {
      "name": "URL NETWORKS",
      "website": "http://www.url.net.au/",
      "logo_url": null,
      "active": true,
      "support_email": "support@url.net.au",
      "support_phone": "1300 33 11 78",
      "id": 142,
      "created_at": "2025-06-20T02:46:43Z",
      "network_details": []
    },
    {
      "name": "VALVE NETWORKS",
      "website": "https://valvenetworks.com.au/",
      "logo_url": null,
      "active": true,
      "support_email": null,
      "support_phone": null,
      "id": 164,
      "created_at": "2025-06-20T02:46:43Z",
      "network_details": []
    },
    {
      "name": "VEETEL",
      "website": "http://www.veetel.com.au/",
      "logo_url": null,
      "active": true,
      "support_email": "enquiries@veetel.com.au",
      "support_phone": "1300 833 835",
      "id": 144,
      "created_at": "2025-06-20T02:46:43Z",
      "network_details": []
    },
    {
      "name": "VODAFONE",
      "website": "https://www.vodafone.com.au/",
      "logo_url": null,
      "active": true,
      "support_email": "",
      "support_phone": "1300 801 122",
      "id": 146,
      "created_at": "2025-06-20T02:46:43Z",
      "network_details": []
    },
    {
      "name": "VOIPEX",
      "website": "https://www.voipex.com.au/",
      "logo_url": null,
      "active": true,
      "support_email": "support@voipex.com.au",
      "support_phone": "02 4957 8997",
      "id": 147,
      "created_at": "2025-06-20T02:46:43Z",
      "network_details": []
    },
    {
      "name": "YOMOJO",
      "website": "https://www.yomojo.com.au/",
      "logo_url": null,
      "active": true,
      "support_email": "",
      "support_phone": "1300 966 656 ",
      "id": 162,
      "created_at": "2025-07-18T11:45:32Z",
      "network_details": []
    },
    {
      "name": "ZETTAGRID",
      "website": "http://www.zetta.net.au/",
      "logo_url": null,
      "active": true,
      "support_email": "support@zettagrid.com",
      "support_phone": "1300 597 656",
      "id": 152,
      "created_at": "2025-06-20T02:46:43Z",
      "network_details": []
    },
    {
      "name": "ZIP CONNECT",
      "website": "https://zipconnect.au/",
      "logo_url": null,
      "active": true,
      "support_email": "info@zipconnect.au",
      "support_phone": "1300 296 655",
      "id": 165,
      "created_at": "2025-06-20T02:46:43Z",
      "network_details": []
    }
  ]
}